MANIFEST.in
README.md
ccv_wrapper.i
libccv.py
numpy.i
setup.py
ccv/lib/.ycm_extra_conf.py
ccv/lib/ccv.h
ccv/lib/ccv_algebra.c
ccv/lib/ccv_basic.c
ccv/lib/ccv_bbf.c
ccv/lib/ccv_cache.c
ccv/lib/ccv_classic.c
ccv/lib/ccv_convnet.c
ccv/lib/ccv_daisy.c
ccv/lib/ccv_dpm.c
ccv/lib/ccv_ferns.c
ccv/lib/ccv_icf.c
ccv/lib/ccv_internal.h
ccv/lib/ccv_io.c
ccv/lib/ccv_memory.c
ccv/lib/ccv_mser.c
ccv/lib/ccv_numeric.c
ccv/lib/ccv_resample.c
ccv/lib/ccv_sift.c
ccv/lib/ccv_sparse_coding.c
ccv/lib/ccv_swt.c
ccv/lib/ccv_tld.c
ccv/lib/ccv_transform.c
ccv/lib/ccv_util.c
ccv/lib/config.mk.in
ccv/lib/configure
ccv/lib/configure.ac
ccv/lib/makefile
ccv/lib/3rdparty/dsfmt/dSFMT-common.h
ccv/lib/3rdparty/dsfmt/dSFMT-params.h
ccv/lib/3rdparty/dsfmt/dSFMT-params19937.h
ccv/lib/3rdparty/dsfmt/dSFMT.c
ccv/lib/3rdparty/dsfmt/dSFMT.h
ccv/lib/3rdparty/kissfft/_kiss_fft_guts.h
ccv/lib/3rdparty/kissfft/_kissf_fft_guts.h
ccv/lib/3rdparty/kissfft/kiss_fft.c
ccv/lib/3rdparty/kissfft/kiss_fft.h
ccv/lib/3rdparty/kissfft/kiss_fftnd.c
ccv/lib/3rdparty/kissfft/kiss_fftnd.h
ccv/lib/3rdparty/kissfft/kiss_fftndr.c
ccv/lib/3rdparty/kissfft/kiss_fftndr.h
ccv/lib/3rdparty/kissfft/kiss_fftr.c
ccv/lib/3rdparty/kissfft/kiss_fftr.h
ccv/lib/3rdparty/kissfft/kissf_fft.c
ccv/lib/3rdparty/kissfft/kissf_fft.h
ccv/lib/3rdparty/kissfft/kissf_fftnd.c
ccv/lib/3rdparty/kissfft/kissf_fftnd.h
ccv/lib/3rdparty/kissfft/kissf_fftndr.c
ccv/lib/3rdparty/kissfft/kissf_fftndr.h
ccv/lib/3rdparty/kissfft/kissf_fftr.c
ccv/lib/3rdparty/kissfft/kissf_fftr.h
ccv/lib/3rdparty/sfmt/SFMT-alti.h
ccv/lib/3rdparty/sfmt/SFMT-common.h
ccv/lib/3rdparty/sfmt/SFMT-params.h
ccv/lib/3rdparty/sfmt/SFMT-params19937.h
ccv/lib/3rdparty/sfmt/SFMT-sse2.h
ccv/lib/3rdparty/sfmt/SFMT.c
ccv/lib/3rdparty/sfmt/SFMT.h
ccv/lib/3rdparty/sha1/sha1.c
ccv/lib/3rdparty/sha1/sha1.h
ccv/lib/3rdparty/sqlite3/sqlite3.c
ccv/lib/3rdparty/sqlite3/sqlite3.h
ccv/lib/cuda/.ycm_extra_conf.py
ccv/lib/cuda/cwc.h
ccv/lib/cuda/cwc_convnet.cu
ccv/lib/cuda/cwc_internal.h
ccv_numpy.egg-info/PKG-INFO
ccv_numpy.egg-info/SOURCES.txt
ccv_numpy.egg-info/dependency_links.txt
ccv_numpy.egg-info/pbr.json
ccv_numpy.egg-info/top_level.txt