Metadata-Version: 2.1
Name: ccv-numpy
Version: 0.0.3
Summary: Wrapper module for ccv using numpy arrays interface
Home-page: https://github.com/r3gis3r/ccv-numpy
Author: r3gis3r
Author-email: r3gis.3r@gmail.com
License: UNKNOWN
Platform: UNKNOWN
Classifier: Development Status :: 3 - Alpha
Classifier: Intended Audience :: Developers
Classifier: License :: OSI Approved :: BSD License
Classifier: Programming Language :: Python :: 2
Classifier: Programming Language :: Python :: 3
Classifier: Programming Language :: Python :: Implementation :: CPython
Classifier: Topic :: Software Development :: Libraries
Classifier: Topic :: Scientific/Engineering :: Image Recognition
